AnD_balance/__init__.py
AnD_balance/balance.py
AnD_balance/comm.py
AnD_balance-0.0.1.dist-info/METADATA
AnD_balance-0.0.1.dist-info/WHEEL
AnD_balance-0.0.1.dist-info/top_level.txt
AnD_balance-0.0.1.dist-info/RECORD
